.gitignore
nidx_protos-6.11.1.post5854.dist-info/METADATA
nidx_protos-6.11.1.post5854.dist-info/WHEEL
nidx_protos-6.11.1.post5854.dist-info/entry_points.txt
nidx_protos/nidx_pb2.py
nidx_protos/nidx_pb2.pyi
nidx_protos/nidx_pb2_grpc.py
nidx_protos/nodereader_pb2.py
nidx_protos/nodereader_pb2.pyi
nidx_protos/noderesources_pb2.py
nidx_protos/noderesources_pb2.pyi
nidx_protos/nodewriter_pb2.py
nidx_protos/nodewriter_pb2.pyi
nidx_protos/py.typed
nidx_protos-6.11.1.post5854.dist-info/RECORD
