Metadata-Version: 2.4
Name: nidx_protos
Version: 6.11.1.post5854
Summary: Protobuf definitions for nucliadb/nidx
Author-Email: Nuclia <nucliadb@nuclia.com>
License-Expression: AGPL-3.0-or-later
Classifier: Development Status :: 4 - Beta
Classifier: Programming Language :: Python
Classifier: Programming Language :: Python :: 3.10
Classifier: Programming Language :: Python :: 3.11
Classifier: Programming Language :: Python :: 3.12
Classifier: Programming Language :: Python :: 3 :: Only
Classifier: Topic :: Software Development :: Libraries :: Python Modules
Project-URL: Homepage, https://nuclia.com
Project-URL: Repository, https://github.com/nuclia/nucliadb
Requires-Python: <4,>=3.10
Requires-Dist: protobuf<7.0.0,>=6.31.1
Provides-Extra: grpc
Requires-Dist: grpcio>=1.76.0; extra == "grpc"
